ripl_articulation/__init__.py
ripl_articulation/estimator.py
ripl_articulation/factors.py
ripl_articulation/utils.py
ripl_articulation-2025.10.20.dist-info/licenses/LICENSE
ripl_articulation-2025.10.20.dist-info/METADATA
ripl_articulation-2025.10.20.dist-info/WHEEL
ripl_articulation-2025.10.20.dist-info/top_level.txt
ripl_articulation-2025.10.20.dist-info/RECORD
