Metadata-Version: 2.4
Name: ripl_articulation
Version: 2025.10.20
Summary: Package containing the articulation estimation tools of the RIPL Lab of the University of Waterloo.
Author-email: Russell Buchanan <russell.buchanan@uwaterloo.ca>, Adrian Röfer <aroefer@cs.uni-freiburg.de>
License-Expression: BSD-3-Clause
Project-URL: Homepage, https://github.com/ripl-lab/ripl_articulation
Project-URL: Issues, https://github.com/ripl-lab/ripl_articulation/issues
Classifier: Programming Language :: Python :: 3
Classifier: Operating System :: OS Independent
Requires-Python: >=3.8
License-File: LICENSE
Requires-Dist: numpy<=1.26.4
Requires-Dist: gtsam>=4.1
Provides-Extra: test
Requires-Dist: scipy>=1.14.0; extra == "test"
Requires-Dist: tqdm; extra == "test"
Requires-Dist: pytest; extra == "test"
Requires-Dist: pytest-cov; extra == "test"
Dynamic: license-file
